pynetlify/__init__.py
pynetlify/__main__.py
pynetlify/cli.py
pynetlify/pynetlify.py
pynetlify-0.1.1.dist-info/LICENSE.txt
pynetlify-0.1.1.dist-info/METADATA
pynetlify-0.1.1.dist-info/WHEEL
pynetlify-0.1.1.dist-info/top_level.txt
pynetlify-0.1.1.dist-info/RECORD
